{
  "checkedAt": "2026-06-28T09:00:49.262Z",
  "sources": [
    {
      "name": "CCTV standings",
      "url": "https://cbs-u.sports.cctv.com/statistics/football/team/rankings?leagueId=3400&season=2026",
      "ok": true,
      "mode": "live",
      "message": "updated from remote source",
      "cache": {
        "exists": true,
        "updatedAt": "2026-06-28T09:00:48.553Z"
      },
      "checkedAt": "2026-06-28T09:00:48.555Z"
    },
    {
      "name": "CCTV scorers",
      "url": "https://cbs-u.sports.cctv.com/statistics/football/player/scorers?leagueId=3400&season=2026",
      "ok": true,
      "mode": "live",
      "message": "updated from remote source",
      "cache": {
        "exists": true,
        "updatedAt": "2026-06-28T09:00:49.104Z"
      },
      "checkedAt": "2026-06-28T09:00:49.105Z"
    },
    {
      "name": "FIFA Watch live scores",
      "url": "https://fifawatch.com/api/match-live.json?lang=zh",
      "ok": true,
      "mode": "live",
      "message": "updated from remote source",
      "cache": {
        "exists": true,
        "updatedAt": "2026-06-28T09:00:49.261Z"
      },
      "checkedAt": "2026-06-28T09:00:49.262Z"
    }
  ]
}
